aiobs/__init__.py
aiobs/collector.py
aiobs/observe.py
aiobs/classifier/__init__.py
aiobs/classifier/base.py
aiobs/classifier/models/__init__.py
aiobs/classifier/models/classification.py
aiobs/classifier/openai/__init__.py
aiobs/classifier/openai/classifier.py
aiobs/evals/__init__.py
aiobs/evals/base.py
aiobs/evals/correctness/__init__.py
aiobs/evals/correctness/ground_truth.py
aiobs/evals/correctness/hallucination_detection.py
aiobs/evals/correctness/regex_assertion.py
aiobs/evals/correctness/schema_assertion.py
aiobs/evals/models/__init__.py
aiobs/evals/models/configs.py
aiobs/evals/models/eval_input.py
aiobs/evals/models/eval_result.py
aiobs/evals/reliability/__init__.py
aiobs/evals/reliability/latency_consistency.py
aiobs/evals/safety/__init__.py
aiobs/evals/safety/pii_detection.py
aiobs/exporters/__init__.py
aiobs/exporters/base.py
aiobs/exporters/custom.py
aiobs/exporters/gcs.py
aiobs/llm/__init__.py
aiobs/llm/anthropic.py
aiobs/llm/base.py
aiobs/llm/factory.py
aiobs/llm/gemini.py
aiobs/llm/openai.py
aiobs/models/__init__.py
aiobs/models/observability.py
aiobs/providers/__init__.py
aiobs/providers/base.py
aiobs/providers/gemini/__init__.py
aiobs/providers/gemini/provider.py
aiobs/providers/gemini/apis/__init__.py
aiobs/providers/gemini/apis/base_api.py
aiobs/providers/gemini/apis/generate_content.py
aiobs/providers/gemini/apis/generate_videos.py
aiobs/providers/gemini/apis/models/__init__.py
aiobs/providers/gemini/apis/models/base.py
aiobs/providers/gemini/apis/models/generate_content.py
aiobs/providers/gemini/apis/models/generate_videos.py
aiobs/providers/openai/__init__.py
aiobs/providers/openai/provider.py
aiobs/providers/openai/apis/__init__.py
aiobs/providers/openai/apis/base_api.py
aiobs/providers/openai/apis/chat_completions.py
aiobs/providers/openai/apis/embeddings.py
aiobs/providers/openai/apis/models/__init__.py
aiobs/providers/openai/apis/models/base.py
aiobs/providers/openai/apis/models/chat_completions.py
aiobs-0.1.5.dist-info/METADATA
aiobs-0.1.5.dist-info/WHEEL
aiobs-0.1.5.dist-info/RECORD
