Metadata-Version: 2.4
Name: aiobs
Version: 0.1.5
Summary: Minimal, extensible LLM observability SDK with OpenAI and Gemini support.
Project-URL: Homepage, https://github.com/neuralis-in/aiobs
Project-URL: Repository, https://github.com/neuralis-in/aiobs
Project-URL: Documentation, https://neuralis-in.github.io/aiobs/
Author: aiobs Authors
Keywords: gemini,genai,llm,observability,openai,tracing
Classifier: Intended Audience :: Developers
Classifier: Programming Language :: Python :: 3
Classifier: Programming Language :: Python :: 3 :: Only
Classifier: Programming Language :: Python :: 3.8
Classifier: Programming Language :: Python :: 3.9
Classifier: Programming Language :: Python :: 3.10
Classifier: Programming Language :: Python :: 3.11
Classifier: Programming Language :: Python :: 3.12
Classifier: Topic :: Software Development :: Libraries
Requires-Python: >=3.8
Requires-Dist: pydantic>=2
Provides-Extra: all
Requires-Dist: google-genai>=1.0.0; extra == 'all'
Requires-Dist: openai<2,>=1.0.0; extra == 'all'
Requires-Dist: python-dotenv>=1.0; extra == 'all'
Provides-Extra: docs
Requires-Dist: furo>=2024.1.29; extra == 'docs'
Requires-Dist: sphinx-copybutton>=0.5; extra == 'docs'
Requires-Dist: sphinx>=7; extra == 'docs'
Provides-Extra: example
Requires-Dist: python-dotenv>=1.0; extra == 'example'
Provides-Extra: gemini
Requires-Dist: google-genai>=1.0.0; extra == 'gemini'
Provides-Extra: openai
Requires-Dist: openai<2,>=1.0.0; extra == 'openai'
Provides-Extra: test
Requires-Dist: pytest>=7; extra == 'test'
